{
  "cookies": [
    {
      "name": "__Host-authjs.csrf-token",
      "value": "eb6fd3c389b175b1700da5bc370fa1a7abdcb170085ae4cea55d5e3897e8e498%7C805372911df31d8ef69137da518f8fe7aec59e5ee7d859fc8f02065751560891",
      "domain": "rhombusai.com",
      "path": "/",
      "expires": -1,
      "httpOnly": true,
      "secure": true,
      "sameSite": "Lax"
    },
    {
      "name": "__Secure-authjs.callback-url",
      "value": "https%3A%2F%2Frhombusai.com%2Fredirect",
      "domain": "rhombusai.com",
      "path": "/",
      "expires": -1,
      "httpOnly": true,
      "secure": true,
      "sameSite": "Lax"
    },
    {
      "name": "_gcl_au",
      "value": "1.1.1554814315.1767771809",
      "domain": ".rhombusai.com",
      "path": "/",
      "expires": 1775547809,
      "httpOnly": false,
      "secure": false,
      "sameSite": "Lax"
    },
    {
      "name": "__cf_bm",
      "value": "krKPiloa3zB7xXiSNXku_T3aZirE1D9bOXzcm8jd8pM-1767771809-1.0.1.1-l1LFxyVv9LgeQ9jkcU7kptb.7QtI_1WxxVr0af770mgD9m.nck6CuIj.A2U6W0Pe1MnKwpoTQgzunmaHk5iyGtsXxcjWJFfOrHPGbiluIL4",
      "domain": ".apollo.io",
      "path": "/",
      "expires": 1767773609.645004,
      "httpOnly": true,
      "secure": true,
      "sameSite": "None"
    },
    {
      "name": "li_sugr",
      "value": "9152ffa0-acfb-4568-b5f4-88ff914287bb",
      "domain": ".linkedin.com",
      "path": "/",
      "expires": 1775547819.528938,
      "httpOnly": false,
      "secure": true,
      "sameSite": "None"
    },
    {
      "name": "bcookie",
      "value": "\"v=2&0ffb735a-65ef-4b5f-8d4b-304c953a7ed1\"",
      "domain": ".linkedin.com",
      "path": "/",
      "expires": 1799307819.529033,
      "httpOnly": false,
      "secure": true,
      "sameSite": "None"
    },
    {
      "name": "lidc",
      "value": "\"b=VGST03:s=V:r=V:a=V:p=V:g=3645:u=1:x=1:i=1767771809:t=1767858209:v=2:sig=AQEmLxlwvTuyY_qkhXYK-p5OCVrcVI2T\"",
      "domain": ".linkedin.com",
      "path": "/",
      "expires": 1767858209.932996,
      "httpOnly": false,
      "secure": true,
      "sameSite": "None"
    },
    {
      "name": "_ga",
      "value": "GA1.1.1332842806.1767771810",
      "domain": ".rhombusai.com",
      "path": "/",
      "expires": 1802331819.195159,
      "httpOnly": false,
      "secure": false,
      "sameSite": "Lax"
    },
    {
      "name": "UserMatchHistory",
      "value": "AQKTJDu3wqs1mQAAAZuXaSmlQZLhW4FdzXqTmktURyDWaJp3TqMKOhy7Ko9UGkLZQOa0KDWNKTOT1Q",
      "domain": ".linkedin.com",
      "path": "/",
      "expires": 1770363810.242985,
      "httpOnly": false,
      "secure": true,
      "sameSite": "None"
    },
    {
      "name": "AnalyticsSyncHistory",
      "value": "AQIhyFSocdu0bQAAAZuXaSmmh6C2ZPP1v8d3K50s4YjvLboH6zDQ373dOFkLvLUbyywZyntsBvpvN0_g0Oy-yA",
      "domain": ".linkedin.com",
      "path": "/",
      "expires": 1770363810.243044,
      "httpOnly": false,
      "secure": true,
      "sameSite": "None"
    },
    {
      "name": "IDE",
      "value": "AHWqTUlQ1pkZsyt5EqW70_rRhtjR5EkMDpsOpPGEiybIc52NT93ffWKrC3uR3_kL",
      "domain": ".doubleclick.net",
      "path": "/",
      "expires": 1802331810.378529,
      "httpOnly": true,
      "secure": true,
      "sameSite": "None"
    },
    {
      "name": "bscookie",
      "value": "\"v=1&20260107074330f58fb3b7-6e15-40b9-86e2-1a8012740c96AQEKI5nZQdUr3N2DnFz7PvDfoJYUKZ4g\"",
      "domain": ".www.linkedin.com",
      "path": "/",
      "expires": 1799307810.542831,
      "httpOnly": true,
      "secure": true,
      "sameSite": "None"
    },
    {
      "name": "__cf_bm",
      "value": "z1m2_Yd.syTVLbyglyurVJHaUTAiQp070Iw2FCFwZQw-1767771810-1.0.1.1-UnB47CIAlyKV6ElOj76JbEUKH4fnz0baDWddvdATQrdffmb6LvG5EbYlWDQC5k_2BPuK1vPK2uIyXl43HP7LTCwDBCsq0KH9.dReP4cCdXc",
      "domain": ".linkedin.com",
      "path": "/",
      "expires": 1767773610.542966,
      "httpOnly": true,
      "secure": true,
      "sameSite": "None"
    },
    {
      "name": "did",
      "value": "s%3Av0%3Af32a29f1-fe34-4bf4-8a35-f254a92fdca9%3A2cd3de584ddebabcc9530fdb61474fae59f5dbc2914089878c6f9a3a8426ff3e.PLgexgmuwop%2B%2Bz9LiNjm0osedO2rEtQ6s6OeZp2DZiY",
      "domain": "auth.rhombusai.com",
      "path": "/",
      "expires": 1799329413.699219,
      "httpOnly": true,
      "secure": true,
      "sameSite": "None"
    },
    {
      "name": "did_compat",
      "value": "s%3Av0%3Af32a29f1-fe34-4bf4-8a35-f254a92fdca9%3A2cd3de584ddebabcc9530fdb61474fae59f5dbc2914089878c6f9a3a8426ff3e.PLgexgmuwop%2B%2Bz9LiNjm0osedO2rEtQ6s6OeZp2DZiY",
      "domain": "auth.rhombusai.com",
      "path": "/",
      "expires": 1799329413.701449,
      "httpOnly": true,
      "secure": true,
      "sameSite": "Lax"
    },
    {
      "name": "auth0",
      "value": "s%3AMJVKW-V06DgY4BpWjmudQRFn12WhD-7-.kzvWBu%2FO0e9MCRKBrUbxyL0lSueu0M0xzqFPurOE%2BmM",
      "domain": "auth.rhombusai.com",
      "path": "/",
      "expires": 1768031014.895066,
      "httpOnly": true,
      "secure": true,
      "sameSite": "None"
    },
    {
      "name": "auth0_compat",
      "value": "s%3AMJVKW-V06DgY4BpWjmudQRFn12WhD-7-.kzvWBu%2FO0e9MCRKBrUbxyL0lSueu0M0xzqFPurOE%2BmM",
      "domain": "auth.rhombusai.com",
      "path": "/",
      "expires": 1768031014.895282,
      "httpOnly": true,
      "secure": true,
      "sameSite": "Lax"
    },
    {
      "name": "_ga_7WGPNP2D5N",
      "value": "GS2.1.s1767771810$o1$g1$t1767771830$j40$l0$h0",
      "domain": ".rhombusai.com",
      "path": "/",
      "expires": 1802331830.546773,
      "httpOnly": false,
      "secure": false,
      "sameSite": "Lax"
    },
    {
      "name": "ph_phc_WlyCXwL5K0q2WU8HyTyQaSVxN8QyuumQLH15krWY9Ne_posthog",
      "value": "%7B%22distinct_id%22%3A%22nisala.jayasinghe1994%40gmail.com%22%2C%22%24sesid%22%3A%5B1767771836641%2C%22019b9769-23c3-79f7-a9d4-68f1c17b8a7f%22%2C1767771808707%5D%2C%22%24epp%22%3Atrue%7D",
      "domain": ".rhombusai.com",
      "path": "/",
      "expires": 1799307836,
      "httpOnly": false,
      "secure": true,
      "sameSite": "Lax"
    },
    {
      "name": "__Secure-authjs.session-token",
      "value": "eyJhbGciOiJkaXIiLCJlbmMiOiJBMjU2Q0JDLUhTNTEyIiwia2lkIjoicTQ0SEs3MHBqcndMTGpZdlAwa0VKQU5KOGJSZF96Z1l5U21WVUlueFNKS3d1dmJ4NlBwUzBBenZROU9wOVdHUG9rOUxIbWNoeUhCcGZvMDY1bkowMEEifQ..JV517NSkTZwWuY55HbFaHw.Vku3YcukDciicJA-7om5NB6fNMccjdbSWHeMWppBGd6BPaUpSFkTqoziD9S6p1OAyqpIi0azUHBzkzl1_d0in-8TZ7UWughkBvUxQS_Uf08_cO88S8lYmpjZ43XeIAN3pzXyeFft2TuGg_XZS9tkiP22n0PzGUUhGS3oi2TtTeTAnYPF8J352qKowc3e6T-xGKPyHDX8BAkSDihVnc25fAO2crnafwmL8XbMg4_7_p9mL4LW5xTV16kOOvuWyXy4V4PVm6pIT1NnCyv2pKak-0QeNnq7oQqTk5LJ_wSEDIlETbeG4uGfx2-184vzykWbTIrsniIpkXcKlHP6FuktaAew-OYob5KZoCI5xc2_W1QfGWHxxEPgMbBI_StpA6V00057ssQXsmJq8mH8t3eJb4qKscq9049_u7uQrD00vNZRkv9g-SPsn26e3heq-8j-qkzlGNgcF6mOinXJtBGyQZcrz9AH_rasWvb4W0t6KBRSqIY3Ogv4CjSBSgU6D6lEbUdVAt6stTCpbagpbEF66LltpK4SkvmRz6ui2k-ePenTxDooxmnOqRn0rd77ZJ0edNeCGKufomUaU7j200BhkuRvbNYUc2X7nwHLwjnr5H-PvI6RZEULn101lCyIOKZB8VL1-Vl_DKQoDulGhGzS7cFAFVTeOxmUPgkGG9TVic6p93ggXyGdiERWyqEWQyESddiWkkc49PGTBoj0lUBYh8F2E_UCEUTzIo3_cx_IlQQuwfanFCLLB8ztLuU-t5nBMQP194FgmZRuAMOdbGDk4qMyW2bh2KvuKsqHMfmMv0n118EjFwchMraHiIR3IEtUDamBBKd9z6rcvy0uJ2vfbyhLVcw8DSu9ea8VLorJ1be8fFpkupYFFz1Xgy7i-GSZS-H-WufyJ8y10Tb3A8MrSow2d8Eftkgaa_Eiuh8fhMq85nOnT21qCo2eOb0R8GdA3GDTmWjl0GF-OmzQKLVszRXeO-luik2ci54ta1o7Z0X5UDmtf-TVSMm8_WxhkQYlT-I7bIB3zPfJff_dR6LV9bHzIIgAirKzFaU54rwvjmdY3PWdZr61ZG_4QqWT8RISlRymYD2MGM-uks8kxIqhYgesh2awMeP5hl2X3cg1QXp3TeiVEbIYiSvZx0bDLNwNYEBh32BpI3ZU7M24CDCph2cCPNVKX_A5wkwllQVK5Ekjx4BCn30xvUq3xaOed7MKQwx2ukI0HApQ_YgNY8mSmtjBArfggiI5ry8f-RcLtMi3wkHW1uNplJZD59Y8T66PvFxnPiZJYhPbzhn5p54IPe3c-uiXd8MhsHl74aGcA78nm0condifV4b6JdJwOMXvpFRg-X94Ig2qAJUr05O2EoDYQPE6-NkKYMv_-wSwUwRdbNzMZZ17uMjM0EyU8vHXzmbsEwxcpZEOrJHq0IR4hvTnoihO0XlXX08r5euYSEd8e_2JsbmfrFv1pAcVvpnZln0-NzA3-JOVXtBT4Gdo3NnOHfhceuFsFuwHE95OM_IIHBi-_nw-bK7J2PABoFibI-iPLKDVa4lCJy-Y21sWjUlBjhINUEudkSmb8Hr0YRB0fApbbvXN2kcx4PCwBgrLe94IyXXpNDYSKN4ZgsLivsmBr1KtFvAUJBFtdt4S7zCti47PXYnxm75RwpPx1I56z2stHykXb6hsmLJI4HohOudbsauNg8UtaWWon9-cvQs.xFfcONz0TEJkfNcmnek3tYszMmEYce3nNMMTmdpWhsE",
      "domain": "rhombusai.com",
      "path": "/",
      "expires": 1770363836.767899,
      "httpOnly": true,
      "secure": true,
      "sameSite": "Lax"
    }
  ],
  "origins": [
    {
      "origin": "https://rhombusai.com",
      "localStorage": [
        {
          "name": "_gcl_ls",
          "value": "{\"schema\":\"gcl\",\"version\":1,\"gcl_ctr\":{\"value\":{\"value\":0,\"timeouts\":0,\"creationTimeMs\":1767771809308},\"expires\":1775547809308}}"
        },
        {
          "name": "ph_phc_WlyCXwL5K0q2WU8HyTyQaSVxN8QyuumQLH15krWY9Ne_posthog",
          "value": "{\"distinct_id\":\"nisala.jayasinghe1994@gmail.com\",\"$sesid\":[1767771836641,\"019b9769-23c3-79f7-a9d4-68f1c17b8a7f\",1767771808707],\"$configured_session_timeout_ms\":1800000,\"$client_session_props\":{\"sessionId\":\"019b9769-23c3-79f7-a9d4-68f1c17b8a7f\",\"props\":{\"initialPathName\":\"/\",\"referringDomain\":\"$direct\",\"utm_source\":null,\"utm_medium\":null,\"utm_campaign\":null,\"utm_content\":null,\"utm_term\":null,\"gclid\":null,\"gad_source\":null,\"gclsrc\":null,\"dclid\":null,\"gbraid\":null,\"wbraid\":null,\"fbclid\":null,\"msclkid\":null,\"twclid\":null,\"li_fat_id\":null,\"mc_cid\":null,\"igshid\":null,\"ttclid\":null,\"rdt_cid\":null}},\"$device_id\":\"019b9769-23c7-7927-ab6e-7034f7a034a9\",\"$user_state\":\"identified\",\"$session_recording_enabled_server_side\":true,\"$console_log_recording_enabled_server_side\":true,\"$session_recording_network_payload_capture\":{\"capturePerformance\":{\"network_timing\":true,\"web_vitals\":false,\"web_vitals_allowed_metrics\":null},\"recordBody\":true},\"$session_recording_canvas_recording\":{\"enabled\":true,\"fps\":3,\"quality\":\"0.4\"},\"$replay_sample_rate\":null,\"$replay_minimum_duration\":null,\"$replay_script_config\":{\"script\":\"posthog-recorder\"},\"$autocapture_disabled_server_side\":false,\"$heatmaps_enabled_server_side\":false,\"$web_vitals_enabled_server_side\":false,\"$web_vitals_allowed_metrics\":null,\"$exception_capture_enabled_server_side\":true,\"$dead_clicks_enabled_server_side\":false,\"$active_feature_flags\":[\"fivetran-3rd-party-data-integration\",\"allow-access-pre-launch\",\"chatbot\",\"async-chat-api\",\"pf-user-onboarding\"],\"$enabled_feature_flags\":{\"fivetran-3rd-party-data-integration\":true,\"allow-access-pre-launch\":true,\"chatbot\":true,\"third-party-integration\":false,\"async-chat-api\":true,\"pf-user-onboarding\":true},\"$feature_flag_payloads\":{},\"$epp\":true,\"$user_id\":\"nisala.jayasinghe1994@gmail.com\",\"$stored_person_properties\":{\"email\":\"nisala.jayasinghe1994@gmail.com\",\"name\":\"nisala.jayasinghe1994@gmail.com\"},\"$flag_call_reported\":{\"fivetran-3rd-party-data-integration\":[\"true\"]}}"
        },
        {
          "name": "apolloAnonId",
          "value": "431d195c-82ec-4492-a039-4c36111e36f4"
        },
        {
          "name": "eventQueue",
          "value": "[]"
        },
        {
          "name": "li_adsId",
          "value": "f8f07131-70a6-44ea-8abb-d6c19984d031"
        },
        {
          "name": "dataset_headers_b39e23414552b9927f87f856e7d10af817aca9b73eab1aed0b33fe9ff2b5a0b0",
          "value": "{\"timestamp\":1767771834013,\"headers\":[[\"id\",\"name\",\"email\",\"signup_date\",\"amount\",\"notes\"],[\"1\",\" \\\"  Alice  \\\"\",\"ALICE@EXAMPLE.COM\",\"2025-01-02\",\"100\",\" \\\" first  \\\"\"],[\"2\",\"Bob\",\"bob@example.com\",\"02/01/2025\",\"100\",\" \\\"\\\"\"],[\"2\",\"Bob\",\"bob@example.com\",\"02/01/2025\",\"100\",\" \\\"duplicate row\\\"\"],[\"3\",\"Charlie  \",\"charlie@example.com\",\"2025/01/04\",\"Unnamed: 4\",\" \\\"missing amount\\\"\"],[\"4\",\"Dana\",\"dana@example.com\",\"invalid_date\",\"250\",\"bad date\"],[\"5\",\"Eve\",\"eve@example.com\",\"2025-01-06\",\"300\",\"ok\"],[\"Unnamed: 0\",\"Unnamed: 1\",\"Unnamed: 2\",\"Unnamed: 3\",\"Unnamed: 4\",\"Unnamed: 5\"],[\"Unnamed: 0\",\"Unnamed: 1\",\"Unnamed: 2\",\"Unnamed: 3\",\"Unnamed: 4\",\"Unnamed: 5\"],[\"Unnamed: 0\",\"Unnamed: 1\",\"Unnamed: 2\",\"Unnamed: 3\",\"Unnamed: 4\",\"Unnamed: 5\"],[\"Unnamed: 0\",\"Unnamed: 1\",\"Unnamed: 2\",\"Unnamed: 3\",\"Unnamed: 4\",\"Unnamed: 5\"],[\"Unnamed: 0\",\"Unnamed: 1\",\"Unnamed: 2\",\"Unnamed: 3\",\"Unnamed: 4\",\"Unnamed: 5\"],[\"Unnamed: 0\",\"Unnamed: 1\",\"Unnamed: 2\",\"Unnamed: 3\",\"Unnamed: 4\",\"Unnamed: 5\"],[\"Unnamed: 0\",\"Unnamed: 1\",\"Unnamed: 2\",\"Unnamed: 3\",\"Unnamed: 4\",\"Unnamed: 5\"],[\"Unnamed: 0\",\"Unnamed: 1\",\"Unnamed: 2\",\"Unnamed: 3\",\"Unnamed: 4\",\"Unnamed: 5\"],[\"Unnamed: 0\",\"Unnamed: 1\",\"Unnamed: 2\",\"Unnamed: 3\",\"Unnamed: 4\",\"Unnamed: 5\"],[\"Unnamed: 0\",\"Unnamed: 1\",\"Unnamed: 2\",\"Unnamed: 3\",\"Unnamed: 4\",\"Unnamed: 5\"],[\"Unnamed: 0\",\"Unnamed: 1\",\"Unnamed: 2\",\"Unnamed: 3\",\"Unnamed: 4\",\"Unnamed: 5\"],[\"Unnamed: 0\",\"Unnamed: 1\",\"Unnamed: 2\",\"Unnamed: 3\",\"Unnamed: 4\",\"Unnamed: 5\"],[\"Unnamed: 0\",\"Unnamed: 1\",\"Unnamed: 2\",\"Unnamed: 3\",\"Unnamed: 4\",\"Unnamed: 5\"],[\"Unnamed: 0\",\"Unnamed: 1\",\"Unnamed: 2\",\"Unnamed: 3\",\"Unnamed: 4\",\"Unnamed: 5\"],[\"Unnamed: 0\",\"Unnamed: 1\",\"Unnamed: 2\",\"Unnamed: 3\",\"Unnamed: 4\",\"Unnamed: 5\"],[\"Unnamed: 0\",\"Unnamed: 1\",\"Unnamed: 2\",\"Unnamed: 3\",\"Unnamed: 4\",\"Unnamed: 5\"],[\"Unnamed: 0\",\"Unnamed: 1\",\"Unnamed: 2\",\"Unnamed: 3\",\"Unnamed: 4\",\"Unnamed: 5\"],[\"Unnamed: 0\",\"Unnamed: 1\",\"Unnamed: 2\",\"Unnamed: 3\",\"Unnamed: 4\",\"Unnamed: 5\"],[\"Unnamed: 0\",\"Unnamed: 1\",\"Unnamed: 2\",\"Unnamed: 3\",\"Unnamed: 4\",\"Unnamed: 5\"],[\"Unnamed: 0\",\"Unnamed: 1\",\"Unnamed: 2\",\"Unnamed: 3\",\"Unnamed: 4\",\"Unnamed: 5\"],[\"Unnamed: 0\",\"Unnamed: 1\",\"Unnamed: 2\",\"Unnamed: 3\",\"Unnamed: 4\",\"Unnamed: 5\"],[\"Unnamed: 0\",\"Unnamed: 1\",\"Unnamed: 2\",\"Unnamed: 3\",\"Unnamed: 4\",\"Unnamed: 5\"],[\"Unnamed: 0\",\"Unnamed: 1\",\"Unnamed: 2\",\"Unnamed: 3\",\"Unnamed: 4\",\"Unnamed: 5\"],[\"Unnamed: 0\",\"Unnamed: 1\",\"Unnamed: 2\",\"Unnamed: 3\",\"Unnamed: 4\",\"Unnamed: 5\"],[\"Unnamed: 0\",\"Unnamed: 1\",\"Unnamed: 2\",\"Unnamed: 3\",\"Unnamed: 4\",\"Unnamed: 5\"],[\"Unnamed: 0\",\"Unnamed: 1\",\"Unnamed: 2\",\"Unnamed: 3\",\"Unnamed: 4\",\"Unnamed: 5\"],[\"Unnamed: 0\",\"Unnamed: 1\",\"Unnamed: 2\",\"Unnamed: 3\",\"Unnamed: 4\",\"Unnamed: 5\"],[\"Unnamed: 0\",\"Unnamed: 1\",\"Unnamed: 2\",\"Unnamed: 3\",\"Unnamed: 4\",\"Unnamed: 5\"],[\"Unnamed: 0\",\"Unnamed: 1\",\"Unnamed: 2\",\"Unnamed: 3\",\"Unnamed: 4\",\"Unnamed: 5\"],[\"Unnamed: 0\",\"Unnamed: 1\",\"Unnamed: 2\",\"Unnamed: 3\",\"Unnamed: 4\",\"Unnamed: 5\"],[\"Unnamed: 0\",\"Unnamed: 1\",\"Unnamed: 2\",\"Unnamed: 3\",\"Unnamed: 4\",\"Unnamed: 5\"],[\"Unnamed: 0\",\"Unnamed: 1\",\"Unnamed: 2\",\"Unnamed: 3\",\"Unnamed: 4\",\"Unnamed: 5\"],[\"Unnamed: 0\",\"Unnamed: 1\",\"Unnamed: 2\",\"Unnamed: 3\",\"Unnamed: 4\",\"Unnamed: 5\"],[\"Unnamed: 0\",\"Unnamed: 1\",\"Unnamed: 2\",\"Unnamed: 3\",\"Unnamed: 4\",\"Unnamed: 5\"],[\"Unnamed: 0\",\"Unnamed: 1\",\"Unnamed: 2\",\"Unnamed: 3\",\"Unnamed: 4\",\"Unnamed: 5\"],[\"Unnamed: 0\",\"Unnamed: 1\",\"Unnamed: 2\",\"Unnamed: 3\",\"Unnamed: 4\",\"Unnamed: 5\"],[\"Unnamed: 0\",\"Unnamed: 1\",\"Unnamed: 2\",\"Unnamed: 3\",\"Unnamed: 4\",\"Unnamed: 5\"],[\"Unnamed: 0\",\"Unnamed: 1\",\"Unnamed: 2\",\"Unnamed: 3\",\"Unnamed: 4\",\"Unnamed: 5\"],[\"Unnamed: 0\",\"Unnamed: 1\",\"Unnamed: 2\",\"Unnamed: 3\",\"Unnamed: 4\",\"Unnamed: 5\"],[\"Unnamed: 0\",\"Unnamed: 1\",\"Unnamed: 2\",\"Unnamed: 3\",\"Unnamed: 4\",\"Unnamed: 5\"],[\"Unnamed: 0\",\"Unnamed: 1\",\"Unnamed: 2\",\"Unnamed: 3\",\"Unnamed: 4\",\"Unnamed: 5\"],[\"Unnamed: 0\",\"Unnamed: 1\",\"Unnamed: 2\",\"Unnamed: 3\",\"Unnamed: 4\",\"Unnamed: 5\"],[\"Unnamed: 0\",\"Unnamed: 1\",\"Unnamed: 2\",\"Unnamed: 3\",\"Unnamed: 4\",\"Unnamed: 5\"],[\"Unnamed: 0\",\"Unnamed: 1\",\"Unnamed: 2\",\"Unnamed: 3\",\"Unnamed: 4\",\"Unnamed: 5\"],[\"Unnamed: 0\",\"Unnamed: 1\",\"Unnamed: 2\",\"Unnamed: 3\",\"Unnamed: 4\",\"Unnamed: 5\"],[\"Unnamed: 0\",\"Unnamed: 1\",\"Unnamed: 2\",\"Unnamed: 3\",\"Unnamed: 4\",\"Unnamed: 5\"],[\"Unnamed: 0\",\"Unnamed: 1\",\"Unnamed: 2\",\"Unnamed: 3\",\"Unnamed: 4\",\"Unnamed: 5\"],[\"Unnamed: 0\",\"Unnamed: 1\",\"Unnamed: 2\",\"Unnamed: 3\",\"Unnamed: 4\",\"Unnamed: 5\"],[\"Unnamed: 0\",\"Unnamed: 1\",\"Unnamed: 2\",\"Unnamed: 3\",\"Unnamed: 4\",\"Unnamed: 5\"],[\"Unnamed: 0\",\"Unnamed: 1\",\"Unnamed: 2\",\"Unnamed: 3\",\"Unnamed: 4\",\"Unnamed: 5\"],[\"Unnamed: 0\",\"Unnamed: 1\",\"Unnamed: 2\",\"Unnamed: 3\",\"Unnamed: 4\",\"Unnamed: 5\"],[\"Unnamed: 0\",\"Unnamed: 1\",\"Unnamed: 2\",\"Unnamed: 3\",\"Unnamed: 4\",\"Unnamed: 5\"],[\"Unnamed: 0\",\"Unnamed: 1\",\"Unnamed: 2\",\"Unnamed: 3\",\"Unnamed: 4\",\"Unnamed: 5\"],[\"Unnamed: 0\",\"Unnamed: 1\",\"Unnamed: 2\",\"Unnamed: 3\",\"Unnamed: 4\",\"Unnamed: 5\"],[\"Unnamed: 0\",\"Unnamed: 1\",\"Unnamed: 2\",\"Unnamed: 3\",\"Unnamed: 4\",\"Unnamed: 5\"],[\"Unnamed: 0\",\"Unnamed: 1\",\"Unnamed: 2\",\"Unnamed: 3\",\"Unnamed: 4\",\"Unnamed: 5\"],[\"Unnamed: 0\",\"Unnamed: 1\",\"Unnamed: 2\",\"Unnamed: 3\",\"Unnamed: 4\",\"Unnamed: 5\"],[\"Unnamed: 0\",\"Unnamed: 1\",\"Unnamed: 2\",\"Unnamed: 3\",\"Unnamed: 4\",\"Unnamed: 5\"],[\"Unnamed: 0\",\"Unnamed: 1\",\"Unnamed: 2\",\"Unnamed: 3\",\"Unnamed: 4\",\"Unnamed: 5\"],[\"Unnamed: 0\",\"Unnamed: 1\",\"Unnamed: 2\",\"Unnamed: 3\",\"Unnamed: 4\",\"Unnamed: 5\"],[\"Unnamed: 0\",\"Unnamed: 1\",\"Unnamed: 2\",\"Unnamed: 3\",\"Unnamed: 4\",\"Unnamed: 5\"],[\"Unnamed: 0\",\"Unnamed: 1\",\"Unnamed: 2\",\"Unnamed: 3\",\"Unnamed: 4\",\"Unnamed: 5\"],[\"Unnamed: 0\",\"Unnamed: 1\",\"Unnamed: 2\",\"Unnamed: 3\",\"Unnamed: 4\",\"Unnamed: 5\"],[\"Unnamed: 0\",\"Unnamed: 1\",\"Unnamed: 2\",\"Unnamed: 3\",\"Unnamed: 4\",\"Unnamed: 5\"],[\"Unnamed: 0\",\"Unnamed: 1\",\"Unnamed: 2\",\"Unnamed: 3\",\"Unnamed: 4\",\"Unnamed: 5\"],[\"Unnamed: 0\",\"Unnamed: 1\",\"Unnamed: 2\",\"Unnamed: 3\",\"Unnamed: 4\",\"Unnamed: 5\"],[\"Unnamed: 0\",\"Unnamed: 1\",\"Unnamed: 2\",\"Unnamed: 3\",\"Unnamed: 4\",\"Unnamed: 5\"],[\"Unnamed: 0\",\"Unnamed: 1\",\"Unnamed: 2\",\"Unnamed: 3\",\"Unnamed: 4\",\"Unnamed: 5\"],[\"Unnamed: 0\",\"Unnamed: 1\",\"Unnamed: 2\",\"Unnamed: 3\",\"Unnamed: 4\",\"Unnamed: 5\"],[\"Unnamed: 0\",\"Unnamed: 1\",\"Unnamed: 2\",\"Unnamed: 3\",\"Unnamed: 4\",\"Unnamed: 5\"],[\"Unnamed: 0\",\"Unnamed: 1\",\"Unnamed: 2\",\"Unnamed: 3\",\"Unnamed: 4\",\"Unnamed: 5\"],[\"Unnamed: 0\",\"Unnamed: 1\",\"Unnamed: 2\",\"Unnamed: 3\",\"Unnamed: 4\",\"Unnamed: 5\"],[\"Unnamed: 0\",\"Unnamed: 1\",\"Unnamed: 2\",\"Unnamed: 3\",\"Unnamed: 4\",\"Unnamed: 5\"],[\"Unnamed: 0\",\"Unnamed: 1\",\"Unnamed: 2\",\"Unnamed: 3\",\"Unnamed: 4\",\"Unnamed: 5\"],[\"Unnamed: 0\",\"Unnamed: 1\",\"Unnamed: 2\",\"Unnamed: 3\",\"Unnamed: 4\",\"Unnamed: 5\"],[\"Unnamed: 0\",\"Unnamed: 1\",\"Unnamed: 2\",\"Unnamed: 3\",\"Unnamed: 4\",\"Unnamed: 5\"],[\"Unnamed: 0\",\"Unnamed: 1\",\"Unnamed: 2\",\"Unnamed: 3\",\"Unnamed: 4\",\"Unnamed: 5\"],[\"Unnamed: 0\",\"Unnamed: 1\",\"Unnamed: 2\",\"Unnamed: 3\",\"Unnamed: 4\",\"Unnamed: 5\"],[\"Unnamed: 0\",\"Unnamed: 1\",\"Unnamed: 2\",\"Unnamed: 3\",\"Unnamed: 4\",\"Unnamed: 5\"],[\"Unnamed: 0\",\"Unnamed: 1\",\"Unnamed: 2\",\"Unnamed: 3\",\"Unnamed: 4\",\"Unnamed: 5\"],[\"Unnamed: 0\",\"Unnamed: 1\",\"Unnamed: 2\",\"Unnamed: 3\",\"Unnamed: 4\",\"Unnamed: 5\"],[\"Unnamed: 0\",\"Unnamed: 1\",\"Unnamed: 2\",\"Unnamed: 3\",\"Unnamed: 4\",\"Unnamed: 5\"],[\"Unnamed: 0\",\"Unnamed: 1\",\"Unnamed: 2\",\"Unnamed: 3\",\"Unnamed: 4\",\"Unnamed: 5\"],[\"Unnamed: 0\",\"Unnamed: 1\",\"Unnamed: 2\",\"Unnamed: 3\",\"Unnamed: 4\",\"Unnamed: 5\"],[\"Unnamed: 0\",\"Unnamed: 1\",\"Unnamed: 2\",\"Unnamed: 3\",\"Unnamed: 4\",\"Unnamed: 5\"],[\"Unnamed: 0\",\"Unnamed: 1\",\"Unnamed: 2\",\"Unnamed: 3\",\"Unnamed: 4\",\"Unnamed: 5\"],[\"Unnamed: 0\",\"Unnamed: 1\",\"Unnamed: 2\",\"Unnamed: 3\",\"Unnamed: 4\",\"Unnamed: 5\"],[\"Unnamed: 0\",\"Unnamed: 1\",\"Unnamed: 2\",\"Unnamed: 3\",\"Unnamed: 4\",\"Unnamed: 5\"],[\"Unnamed: 0\",\"Unnamed: 1\",\"Unnamed: 2\",\"Unnamed: 3\",\"Unnamed: 4\",\"Unnamed: 5\"],[\"Unnamed: 0\",\"Unnamed: 1\",\"Unnamed: 2\",\"Unnamed: 3\",\"Unnamed: 4\",\"Unnamed: 5\"],[\"Unnamed: 0\",\"Unnamed: 1\",\"Unnamed: 2\",\"Unnamed: 3\",\"Unnamed: 4\",\"Unnamed: 5\"],[\"Unnamed: 0\",\"Unnamed: 1\",\"Unnamed: 2\",\"Unnamed: 3\",\"Unnamed: 4\",\"Unnamed: 5\"],[\"Unnamed: 0\",\"Unnamed: 1\",\"Unnamed: 2\",\"Unnamed: 3\",\"Unnamed: 4\",\"Unnamed: 5\"]],\"fileHash\":\"b39e23414552b9927f87f856e7d10af817aca9b73eab1aed0b33fe9ff2b5a0b0\"}"
        },
        {
          "name": "chatbot-processing-state",
          "value": "true"
        }
      ]
    }
  ]
}